akasha_plus/__init__.py
akasha_plus/cli.py
akasha_plus/convert.py
akasha_plus/gptq.py
akasha_plus/quantize_linux
akasha_plus/quantize_mac
akasha_plus/quantize_win.exe
akasha_plus/agents/__init__.py
akasha_plus/agents/default_prompts.py
akasha_plus/agents/tools.py
akasha_plus-0.3.17.dist-info/License
akasha_plus-0.3.17.dist-info/METADATA
akasha_plus-0.3.17.dist-info/WHEEL
akasha_plus-0.3.17.dist-info/entry_points.txt
akasha_plus-0.3.17.dist-info/top_level.txt
akasha_plus-0.3.17.dist-info/RECORD
