Metadata-Version: 2.1
Name: akasha-plus
Version: 0.3.17
Summary: Extension tools for akasha-terminal
Author: shihiyang
Author-email: shihiyang@iii.org.tw
Requires-Python: >=3.8
License-File: License
Requires-Dist: akasha-terminal ==0.8.47
Requires-Dist: numpy ~=1.24.4
Requires-Dist: sentencepiece ~=0.1.98
Requires-Dist: transformers <5.0.0,>=4.35.2
Requires-Dist: gguf >=0.1.0
Requires-Dist: protobuf <5.0.0,>=4.21.0
Requires-Dist: torch ~=2.0.1
Requires-Dist: einops ~=0.7.0
Requires-Dist: click
Requires-Dist: auto-gptq >=0.3.1
Requires-Dist: psycopg2 ==2.9.9
Requires-Dist: pandas ==2.2.2
Requires-Dist: pymssql ==2.3.0
Requires-Dist: mysql-connector-python ==9.0.0
